macop/__init__.py
macop/algorithms/__init__.py
macop/algorithms/base.py
macop/algorithms/mono.py
macop/algorithms/multi.py
macop/callbacks/__init__.py
macop/callbacks/base.py
macop/callbacks/classicals.py
macop/callbacks/multi.py
macop/callbacks/policies.py
macop/evaluators/__init__.py
macop/evaluators/base.py
macop/evaluators/continuous/__init__.py
macop/evaluators/continuous/mono.py
macop/evaluators/continuous/multi.py
macop/evaluators/discrete/__init__.py
macop/evaluators/discrete/mono.py
macop/evaluators/discrete/multi.py
macop/operators/__init__.py
macop/operators/base.py
macop/operators/continuous/__init__.py
macop/operators/continuous/crossovers.py
macop/operators/continuous/mutators.py
macop/operators/discrete/__init__.py
macop/operators/discrete/crossovers.py
macop/operators/discrete/mutators.py
macop/policies/__init__.py
macop/policies/base.py
macop/policies/classicals.py
macop/policies/reinforcement.py
macop/solutions/__init__.py
macop/solutions/base.py
macop/solutions/continuous.py
macop/solutions/discrete.py
macop/utils/__init__.py
macop/utils/progress.py
macop-1.2.0.dist-info/LICENSE
macop-1.2.0.dist-info/METADATA
macop-1.2.0.dist-info/WHEEL
macop-1.2.0.dist-info/top_level.txt
macop-1.2.0.dist-info/RECORD
