Metadata-Version: 2.1
Name: macop
Version: 1.2.0
Summary: Minimalist And Customisable Optimisation Package
Home-page: https://github.com/prise-3d/macop
Author: Jérôme BUISINE
Author-email: jerome.buisine@univ-littoral.fr
License: MIT
Platform: UNKNOWN
Classifier: Development Status :: 5 - Production/Stable
Classifier: License :: OSI Approved :: MIT License
Classifier: Programming Language :: Python :: 3.8
Classifier: Topic :: Scientific/Engineering
Classifier: Topic :: Utilities
Requires-Dist: numpy
